pydecisionforest/__init__.py
pydecisionforest/adaboost.py
pydecisionforest/core.py
pydecisionforest/decision_forest.py
pydecisionforest/decision_tree.py
pydecisionforest-0.1.2.dist-info/licenses/LICENSE
pydecisionforest-0.1.2.dist-info/METADATA
pydecisionforest-0.1.2.dist-info/WHEEL
pydecisionforest-0.1.2.dist-info/top_level.txt
pydecisionforest-0.1.2.dist-info/RECORD
