Metadata-Version: 2.4
Name: pydecisionforest
Version: 0.1.2
Summary: Python implementation of Decision Tree, Decision Forest, and AdaBoost
Author: Quan Wang
Author-email: wangq10@rpi.edu
Classifier: Programming Language :: Python :: 3
Classifier: License :: OSI Approved :: MIT License
Classifier: Operating System :: OS Independent
Requires-Python: >=3.6
License-File: LICENSE
Requires-Dist: numpy>=1.18.0
Dynamic: author
Dynamic: author-email
Dynamic: classifier
Dynamic: description
Dynamic: description-content-type
Dynamic: license-file
Dynamic: requires-dist
Dynamic: requires-python
Dynamic: summary
